{"note":"This file is an internal implementation detail to speed up HTML report generation. Its format can change at any time. You might be looking for the JSON report: https://coverage.rtfd.io/cmd.html#cmd-json","format":5,"version":"7.6.0","globals":"61f85eb6c4d430aad244e47d79ad6813","files":{"category_py":{"hash":"a7e89b0fb66157c4e641468da34c985d","index":{"url":"category_py.html","file":"category.py","description":"","nums":{"precision":0,"n_files":1,"n_statements":14,"n_excluded":0,"n_missing":1,"n_branches":0,"n_partial_branches":0,"n_missing_branches":0}}},"main_py":{"hash":"b77584ee39d5909a36801f928e50875d","index":{"url":"main_py.html","file":"main.py","description":"","nums":{"precision":0,"n_files":1,"n_statements":15,"n_excluded":0,"n_missing":15,"n_branches":0,"n_partial_branches":0,"n_missing_branches":0}}},"product_py":{"hash":"2b99524ae98f25f61f8f10be96547807","index":{"url":"product_py.html","file":"product.py","description":"","nums":{"precision":0,"n_files":1,"n_statements":24,"n_excluded":0,"n_missing":3,"n_branches":0,"n_partial_branches":0,"n_missing_branches":0}}},"test_product_py":{"hash":"483cc566a7be29cd439c5878f949dea9","index":{"url":"test_product_py.html","file":"test_product.py","description":"","nums":{"precision":0,"n_files":1,"n_statements":17,"n_excluded":0,"n_missing":1,"n_branches":0,"n_partial_branches":0,"n_missing_branches":0}}}}}